{
    "dspn": {
	"cortical_background": {
	    "generator": "poisson",
	    "frequency": 2,
	    "correlation": 0,
	    "mod_file": "tmGlutPlast",
	    "parameter_file": "../../data/JSON/synapse-param-plasticity.json"
	},
	"!thalamic_background": {
	    "generator": "poisson",
	    "frequency": 2
	},
	"cortical": {
	    "generator": "poisson",
	    "frequency": 5,
	    "mod_file": "tmGlutPlast",
	    "parameter_file": "../../data/JSON/synapse-param-plasticity.json"
	    
	},
	"!thalamic": {
	    "generator": "poisson",
	    "frequency": 0
	}
	
    }
}
